entropy_estimators/__init__.py
entropy_estimators/continuous.py
tests/__init__.py
tests/test_continuous.py
entropy_estimators-0.0.2.dist-info/LICENSE
entropy_estimators-0.0.2.dist-info/METADATA
entropy_estimators-0.0.2.dist-info/WHEEL
entropy_estimators-0.0.2.dist-info/top_level.txt
entropy_estimators-0.0.2.dist-info/RECORD
