Metadata-Version: 2.1
Name: entropy-estimators
Version: 0.0.2
Summary: Estimators for entropy and other information theoretic quantities of continuous distributions
Home-page: https://github.com/paulbrodersen/entropy_estimators
Download-URL: https://github.com/paulbrodersen/entropy_estimators/archive/0.0.2.tar.gz
Author: Paul Brodersen
Author-email: paulbrodersen+entropy_estimators@gmail.com
Keywords: entropy,Shannon information,mutual information,transfer entropy
Platform: Platform Independent
Classifier: Development Status :: 3 - Alpha
Classifier: Intended Audience :: Science/Research
Classifier: License :: OSI Approved :: GNU General Public License v3 (GPLv3)
Classifier: Operating System :: OS Independent
Classifier: Programming Language :: Python :: 3
Classifier: Topic :: Scientific/Engineering :: Mathematics
Classifier: Topic :: Scientific/Engineering :: Physics
License-File: LICENSE
Requires-Dist: scipy
Requires-Dist: numpy
